{
  "data": {
    "calibration": {
      "edges": [
        {
          "node": {
            "id": "Q2FsaWJyYXRpb25Ob2RlOjQ5",
            "idInt": 49,
            "start": "2023-08-01T18:21:59+00:00",
            "end": "2023-08-01T18:21:59+00:00",
            "allProjects": "TPA",
            "nObservations": 1,
            "nAntMin": 31,
            "nAntMax": 31,
            "totalIntegrationTimeSeconds": 120.26899999999999
          }
        },
        {
          "node": {
            "id": "Q2FsaWJyYXRpb25Ob2RlOjUx",
            "idInt": 51,
            "start": "2023-06-27T11:37:31+00:00",
            "end": "2023-06-27T11:37:31+00:00",
            "allProjects": "GC",
            "nObservations": 1,
            "nAntMin": 58,
            "nAntMax": 58,
            "totalIntegrationTimeSeconds": 14399.068999999645
          }
        },
        {
          "node": {
            "id": "Q2FsaWJyYXRpb25Ob2RlOjU0",
            "idInt": 54,
            "start": "2020-07-10T05:07:28+00:00",
            "end": "2020-07-10T05:07:28+00:00",
            "allProjects": "PTA",
            "nObservations": 1,
            "nAntMin": 28,
            "nAntMax": 28,
            "totalIntegrationTimeSeconds": 1023.2854023529411
          }
        },
        {
          "node": {
            "id": "Q2FsaWJyYXRpb25Ob2RlOjUw",
            "idInt": 50,
            "start": "2020-03-15T22:58:52+00:00",
            "end": "2020-03-15T22:58:52+00:00",
            "allProjects": "TPA",
            "nObservations": 1,
            "nAntMin": 57,
            "nAntMax": 57,
            "totalIntegrationTimeSeconds": 466.3350000000006
          }
        },
        {
          "node": {
            "id": "Q2FsaWJyYXRpb25Ob2RlOjUz",
            "idInt": 53,
            "start": "2019-05-14T10:14:18+00:00",
            "end": "2019-05-14T10:14:18+00:00",
            "allProjects": "PTA",
            "nObservations": 1,
            "nAntMin": 54,
            "nAntMax": 54,
            "totalIntegrationTimeSeconds": 1039.9999999999998
          }
        },
        {
          "node": {
            "id": "Q2FsaWJyYXRpb25Ob2RlOjUy",
            "idInt": 52,
            "start": "2019-04-23T06:11:30+00:00",
            "end": "2019-04-23T06:11:30+00:00",
            "allProjects": "PTA",
            "nObservations": 1,
            "nAntMin": 56,
            "nAntMax": 56,
            "totalIntegrationTimeSeconds": 263.99999999999994
          }
        }
      ]
    }
  }
}